{"PlayerName":"Name","StarsCollected":0,"CoinsCollected":0,"GoldCoinsCollected":20,"DiamondCoinsCollected":0,"MusicVolume":1.0,"SFXVolume":1.0,"AutoRetryEnabled":true,"AutoCheckpointsEnabled":true,"ProgressBarEnabled":true,"ShowPercentEnabled":true,"PlayerColor1":{"r":0.4784314,"g":0.9686275,"b":0.003921569},"PlayerColor2":{"r":0.01568628,"g":0.9529412,"b":0.9686275},"myDictionary":{"gamemode":[0,1,0,1,0,1,0,1,0,1,0,1,0,1,0,1,0,1,0,1,0,1,0,1,0,1,0,1,0,1,0,1,0,1,0,1,0,1,0,1,0,1,0,1,0,1,0,1,0,1,0,1,0,1,0,1,0,1,0,1,0,1,0,1,0,1,0,1,0,1,0,1,0,1,0,1,0,1,0,1,0,1,0,1,0,1,0,1,0,1,0,1,0,1,0,1,0,1,0,1,0,1,0,1,0,1,0,1,0,1,0,1,0,1,0,1,0,1,0,1,0,1,0,1,0,1,0,1,0,1,0,1,0,1,0,1,0,1,0,1,0,1,0,1,0,1,0,1,0,1,0,1,0,1,0,1,0,1,0,1,0,1,0,1,0,1,0,1,0,1,0,1,0,1,0,1,0,1,0,1,0,1,0,1,0,1,0,1,0,1,0,1,0,1,0,1,0,1,0,1,0,1,0,1,0,1,0,1,0,1,0,1,0,1,0,1,0,1,0,1,0,1,0,1,0,1,0,1,0,1,0,1,0,1,0,1,0,1,0,1,0,1,0,1,0,1,0,1,0,1,0,1,0,1,0,1,0,1,0,1,0,1,0,1,0,1,0,1,0,1,0,1,0,1,0,1,0,1,0,1,0,1,0,1,0,1,0,1,0,1,0,1,0,1,0,1,0,1,0,1,0,1,0,1,0,1,0,1,0,1,0,1,0,1,0,1,0,1,0,1,0,1,0,1,0,1,0,1,0,1,0,1,0,1,0,1,0,1,0,1,0,1,0,1,0,1,0,1,0,1,0,1,0,1,0,1,0,1,0,1,0,1,0,1,0,1,0,1,0,1,0,1,0,1,0,1,0,1,0,1,0,1,0,1,0,1,0,1,0,1,0,1,0,1,0,1,0,1,0,1,0,1,0,1,0,1,0,1,0,1,0,1,0,1,0,1,0,1,0,1,0,1,0,1,0,1,0,1,0,1,0,1,0,1,0,1,0,1,0,1,0,1,0,1,0,1,0,1,0,1,0,1,0,1,0,1,0,1,0,1,0,1,0,1,0,1,0,1,0,1,0,1,0,1,0,1,0,1,0,1,0,1,0,1,0,1,0,1,0,1,0,1,0,1,0,1,0,1,0,1,0,1,0,1,0,1,0,1,0,1,0,1,0,1,0,1,0,1,0,1,0,1,0,1,0,1,0,1,0,1,0,1,0,1,0,1,0,1,0,1,0,1,0,1,0,1,0,1,0,1,0,1,0,1,0,1,0,1,0,1,0,1,0,1,0,1,0,1,0,1,0,1,0,1,0,1,0,1,0,1,0,1,0,1,0,1,0,1,0,1,0,1,0,1,0,1,0,1,0,1,0,1,0,1,0,1,0,1,0,1,0,1,0,1,0,1,0,1,0,1,0,1,0,1,0,1,0,1,0,1,0,1,0,1,0,1,0,1,0,1,0,1,0,1,0,1,0,1,0,1,0,1,0,1,0,1,0,1,0,1,0,1,0,1,0,1,0,1,0,1,0,1,0,1,0,1,0,1,0,1,0,1,0,1],"cubeIndex":[3],"shipIndex":[2]},"IconData":[{"Gamemode":0,"Index":3},{"Gamemode":1,"Index":2}],"LevelData":[{"Name":"Back On Track","NormalPercent":1.0,"PracticePercent":0.0,"GottenCoins":[false,false,false],"TotalAttempts":0,"TotalJumps":2450,"CompletedLevel":true,"CompletedLevelPractice":false},{"Name":"Stereo Madness","NormalPercent":0.6513147,"PracticePercent":0.0416891575,"GottenCoins":[false,false,false],"TotalAttempts":17,"TotalJumps":428,"CompletedLevel":false,"CompletedLevelPractice":false},{"Name":"Polargeist","NormalPercent":0.8098074,"PracticePercent":0.0,"GottenCoins":[false,false,false],"TotalAttempts":0,"TotalJumps":429,"CompletedLevel":false,"CompletedLevelPractice":false},{"Name":"Dry Out","NormalPercent":0.408968776,"PracticePercent":0.0,"GottenCoins":[false,false,false],"TotalAttempts":0,"TotalJumps":764,"CompletedLevel":false,"CompletedLevelPractice":false},{"Name":"Cant Let Go","NormalPercent":0.8561087,"PracticePercent":0.0,"GottenCoins":[false,false,false],"TotalAttempts":0,"TotalJumps":1102,"CompletedLevel":false,"CompletedLevelPractice":false}]}